README.md
setup.cfg
setup.py
cryptopass/__init__.py
cryptopass/config.py
cryptopass/console.py
cryptopass/encrypt.py
cryptopass/user_managment.py
cryptopass.egg-info/PKG-INFO
cryptopass.egg-info/SOURCES.txt
cryptopass.egg-info/dependency_links.txt
cryptopass.egg-info/entry_points.txt
cryptopass.egg-info/requires.txt
cryptopass.egg-info/top_level.txt