Metadata-Version: 1.0
Name: cryptopass
Version: 0.0.10
Summary: Safe and simple passwords manager
Home-page: https://github.com/francof2a/cryptopass
Author: f2a
Author-email: empty@empty.com
License: MIT
Keywords: password,safe,store
Platform: UNKNOWN
